odoo9_addon_marketing_crm_partner-9.0.1.0.0-py2.7-nspkg.pth
odoo_addons/marketing_crm_partner/__openerp__.py
odoo_addons/marketing_crm_partner/__init__.py
odoo_addons/marketing_crm_partner/README.rst
odoo_addons/marketing_crm_partner/models/res_partner.py
odoo_addons/marketing_crm_partner/models/__init__.py
odoo_addons/marketing_crm_partner/models/crm_lead.py
odoo_addons/marketing_crm_partner/i18n/it.po
odoo_addons/marketing_crm_partner/i18n/es.po
odoo_addons/marketing_crm_partner/i18n/hr.po
odoo_addons/marketing_crm_partner/i18n/bg.po
odoo_addons/marketing_crm_partner/i18n/sl.po
odoo_addons/marketing_crm_partner/i18n/nl.po
odoo_addons/marketing_crm_partner/i18n/de.po
odoo_addons/marketing_crm_partner/i18n/fr.po
odoo_addons/marketing_crm_partner/i18n/pt_BR.po
odoo_addons/marketing_crm_partner/views/res_partner_view.xml
odoo_addons/marketing_crm_partner/tests/test_lead.py
odoo_addons/marketing_crm_partner/tests/__init__.py
odoo_addons/marketing_crm_partner/images/form.png
odoo_addons/marketing_crm_partner/static/description/icon.png
odoo9_addon_marketing_crm_partner-9.0.1.0.0.dist-info/top_level.txt
odoo9_addon_marketing_crm_partner-9.0.1.0.0.dist-info/WHEEL
odoo9_addon_marketing_crm_partner-9.0.1.0.0.dist-info/RECORD
odoo9_addon_marketing_crm_partner-9.0.1.0.0.dist-info/metadata.json
odoo9_addon_marketing_crm_partner-9.0.1.0.0.dist-info/DESCRIPTION.rst
odoo9_addon_marketing_crm_partner-9.0.1.0.0.dist-info/METADATA
odoo9_addon_marketing_crm_partner-9.0.1.0.0.dist-info/namespace_packages.txt
